{
	"info": {
		"_postman_id": "aa3a0cae-c251-4be8-b2ec-e1041553eaca",
		"name": "laravel-lesson",
		"schema": "https://schema.getpostman.com/json/collection/v2.1.0/collection.json"
	},
	"item": [
		{
			"name": "index",
			"request": {
				"auth": {
					"type": "bearer",
					"bearer": [
						{
							"key": "token",
							"value": "{{ApiToken}}",
							"type": "string"
						}
					]
				},
				"method": "GET",
				"header": [
					{
						"key": "Accept",
						"value": "application/json",
						"type": "default"
					}
				],
				"url": {
					"raw": "http://127.0.0.1:8000/api/employees",
					"protocol": "http",
					"host": [
						"127",
						"0",
						"0",
						"1"
					],
					"port": "8000",
					"path": [
						"api",
						"employees"
					]
				}
			},
			"response": []
		},
		{
			"name": "store",
			"request": {
				"auth": {
					"type": "bearer",
					"bearer": [
						{
							"key": "token",
							"value": "{{ApiToken}}",
							"type": "string"
						}
					]
				},
				"method": "POST",
				"header": [
					{
						"key": "Accept",
						"value": "application/json",
						"type": "default"
					}
				],
				"body": {
					"mode": "urlencoded",
					"urlencoded": [
						{
							"key": "first_name",
							"value": "john",
							"type": "default"
						},
						{
							"key": "last_name",
							"value": "doe",
							"type": "default"
						},
						{
							"key": "email",
							"value": "jdoe@email.com",
							"type": "default"
						},
						{
							"key": "age",
							"value": "20",
							"type": "default"
						},
						{
							"key": "gender",
							"value": "Male",
							"type": "default"
						}
					]
				},
				"url": {
					"raw": "http://127.0.0.1:8000/api/employees",
					"protocol": "http",
					"host": [
						"127",
						"0",
						"0",
						"1"
					],
					"port": "8000",
					"path": [
						"api",
						"employees"
					]
				}
			},
			"response": []
		},
		{
			"name": "show",
			"protocolProfileBehavior": {
				"disableBodyPruning": true
			},
			"request": {
				"auth": {
					"type": "bearer",
					"bearer": [
						{
							"key": "token",
							"value": "{{ApiToken}}",
							"type": "string"
						}
					]
				},
				"method": "GET",
				"header": [
					{
						"key": "Accept",
						"value": "application/json",
						"type": "default"
					}
				],
				"body": {
					"mode": "urlencoded",
					"urlencoded": []
				},
				"url": {
					"raw": "http://127.0.0.1:8000/api/employees/7",
					"protocol": "http",
					"host": [
						"127",
						"0",
						"0",
						"1"
					],
					"port": "8000",
					"path": [
						"api",
						"employees",
						"7"
					]
				}
			},
			"response": []
		},
		{
			"name": "delete",
			"request": {
				"auth": {
					"type": "bearer",
					"bearer": [
						{
							"key": "token",
							"value": "{{ApiToken}}",
							"type": "string"
						}
					]
				},
				"method": "DELETE",
				"header": [],
				"url": {
					"raw": "http://127.0.0.1:8000/api/employees/64",
					"protocol": "http",
					"host": [
						"127",
						"0",
						"0",
						"1"
					],
					"port": "8000",
					"path": [
						"api",
						"employees",
						"64"
					]
				}
			},
			"response": []
		},
		{
			"name": "update",
			"request": {
				"auth": {
					"type": "bearer",
					"bearer": [
						{
							"key": "token",
							"value": "{{ApiToken}}",
							"type": "string"
						}
					]
				},
				"method": "PATCH",
				"header": [
					{
						"key": "Accept",
						"value": "application/json",
						"type": "default"
					}
				],
				"body": {
					"mode": "urlencoded",
					"urlencoded": [
						{
							"key": "email",
							"value": "jdoe2@email.com",
							"type": "default"
						}
					]
				},
				"url": {
					"raw": "http://127.0.0.1:8000/api/employees/67",
					"protocol": "http",
					"host": [
						"127",
						"0",
						"0",
						"1"
					],
					"port": "8000",
					"path": [
						"api",
						"employees",
						"67"
					]
				}
			},
			"response": []
		},
		{
			"name": "login",
			"request": {
				"method": "POST",
				"header": [
					{
						"key": "Accept",
						"value": "application/json",
						"type": "default"
					}
				],
				"body": {
					"mode": "urlencoded",
					"urlencoded": [
						{
							"key": "email",
							"value": "admin@email.com",
							"type": "default"
						},
						{
							"key": "password",
							"value": "password",
							"type": "default"
						}
					]
				},
				"url": {
					"raw": "http://127.0.0.1:8000/api/login",
					"protocol": "http",
					"host": [
						"127",
						"0",
						"0",
						"1"
					],
					"port": "8000",
					"path": [
						"api",
						"login"
					]
				}
			},
			"response": []
		},
		{
			"name": "logout",
			"request": {
				"auth": {
					"type": "bearer",
					"bearer": [
						{
							"key": "token",
							"value": "{{ApiToken}}",
							"type": "string"
						}
					]
				},
				"method": "POST",
				"header": [
					{
						"key": "Accept",
						"value": "application/json",
						"type": "default"
					}
				],
				"body": {
					"mode": "urlencoded",
					"urlencoded": []
				},
				"url": {
					"raw": "http://127.0.0.1:8000/api/logout",
					"protocol": "http",
					"host": [
						"127",
						"0",
						"0",
						"1"
					],
					"port": "8000",
					"path": [
						"api",
						"logout"
					]
				}
			},
			"response": []
		}
	]
}